CHANGELOG.md
LICENSE
MANIFEST.in
README.md
setup.py
gitime/__init__.py
gitime/cli.py
gitime/commands.py
gitime/commit.py
gitime/database.py
gitime/invoice.py
gitime/user.py
gitime.egg-info/PKG-INFO
gitime.egg-info/SOURCES.txt
gitime.egg-info/dependency_links.txt
gitime.egg-info/entry_points.txt
gitime.egg-info/requires.txt
gitime.egg-info/top_level.txt