Metadata-Version: 1.1
Name: gitime
Version: 1.0.0
Summary: Build an invoice with your tasks and hours worked from your commit messages
Home-page: https://github.com/jongoodnow/gitime
Author: Jonathan Goodnow
Author-email: goodnow.jonathan@gmail.com
License: MIT
Keywords: git,invoice,timer
Platform: UNKNOWN
Classifier: Development Status :: 3 - Alpha
Classifier: Intended Audience :: Developers
Classifier: License :: OSI Approved :: MIT License
Classifier: Natural Language :: English
Classifier: Operating System :: OS Independent
Classifier: Programming Language :: Python :: 2.7
Classifier: Topic :: Utilities
